sycomore/__init__.py
sycomore/_sycomore.cp37-win_amd64.pyd
sycomore/_sycomore.lib
sycomore/bloch.py
sycomore-1.3.2.dist-info/LICENSE
sycomore-1.3.2.dist-info/METADATA
sycomore-1.3.2.dist-info/WHEEL
sycomore-1.3.2.dist-info/top_level.txt
sycomore-1.3.2.dist-info/RECORD
