Metadata-Version: 2.1
Name: sycomore
Version: 1.3.2
Summary: MRI simulation toolkit
Home-page: https://sycomore.readthedocs.io/
Author: Julien Lamy
Author-email: lamy@unistra.fr
License: MIT
Keywords: MRI,simulation,EPG,Bloch
Platform: UNKNOWN
Classifier: Development Status :: 5 - Production/Stable
Classifier: Environment :: Console
Classifier: Intended Audience :: Education
Classifier: Intended Audience :: Healthcare Industry
Classifier: Intended Audience :: Science/Research
Classifier: License :: OSI Approved :: MIT License
Classifier: Programming Language :: Python :: 3
Classifier: Topic :: Scientific/Engineering :: Medical Science Apps.
Classifier: Topic :: Scientific/Engineering :: Physics
Requires-Python: >=3.5
License-File: LICENSE
